fol/__init__.py
fol/controls/__init__.py
fol/controls/control.py
fol/controls/fourier_control.py
fol/controls/identity_control.py
fol/controls/voronoi_control2D.py
fol/controls/voronoi_control3D.py
fol/data_generators/data_generator.py
fol/data_generators/fem_data_generator.py
fol/data_input_output/data_io.py
fol/data_input_output/zarr_io.py
fol/deep_neural_networks/__init__.py
fol/deep_neural_networks/deep_network.py
fol/deep_neural_networks/deep_o_net_parametric_operator_learning.py
fol/deep_neural_networks/deep_o_nets.py
fol/deep_neural_networks/explicit_parametric_operator_learning.py
fol/deep_neural_networks/fourier_neural_operator_networks.py
fol/deep_neural_networks/fourier_parametric_operator_learning.py
fol/deep_neural_networks/implicit_parametric_operator_learning.py
fol/deep_neural_networks/meta_alpha_meta_implicit_parametric_operator_learning.py
fol/deep_neural_networks/meta_implicit_parametric_operator_learning.py
fol/deep_neural_networks/nns.py
fol/geometries/__init__.py
fol/geometries/geometry.py
fol/geometries/hexahedra_3d_8.py
fol/geometries/quadrilateral_2d_4.py
fol/geometries/tetrahedra_3d_4.py
fol/geometries/triangle_2d_3.py
fol/loss_functions/__init__.py
fol/loss_functions/fe_loss.py
fol/loss_functions/loss.py
fol/loss_functions/mechanical.py
fol/loss_functions/mechanical_neohooke.py
fol/loss_functions/phase_field.py
fol/loss_functions/regression_loss.py
fol/loss_functions/thermal.py
fol/loss_functions/transient_thermal.py
fol/mesh_input_output/__init__.py
fol/mesh_input_output/mesh.py
fol/responses/fe_response.py
fol/responses/response.py
fol/solvers/__init__.py
fol/solvers/adjoint_fe_solver.py
fol/solvers/fe_linear_residual_based_solver.py
fol/solvers/fe_nonlinear_residual_based_solver.py
fol/solvers/fe_solver.py
fol/solvers/solver.py
fol/tools/__init__.py
fol/tools/decoration_functions.py
fol/tools/fem_utilities.py
fol/tools/logging_functions.py
fol/tools/usefull_functions.py
folax-0.0.2.dist-info/METADATA
folax-0.0.2.dist-info/WHEEL
folax-0.0.2.dist-info/licenses/LICENSE
folax-0.0.2.dist-info/RECORD
