Metadata-Version: 2.4
Name: folax
Version: 0.0.2
Summary: A framework for solving and optimizing PDEs by integrating machine learning with numerical methods in computational mechanics.
Author: Reza Najian Asl, email = <reza.najian-asl@tum.de>
License: BSD 4-Clause License
License-File: LICENSE
Keywords: Numerical-Simulation-Optimization,PDE-Solver,Physics-Informed-Neural-Networks (PINNs),Scientific Machine Learning (SciML)
Requires-Python: >=3.10
Requires-Dist: dask
Requires-Dist: flax~=0.10.7
Requires-Dist: gmsh
Requires-Dist: h5py
Requires-Dist: matplotlib
Requires-Dist: meshio
Requires-Dist: numpy
Requires-Dist: optax
Requires-Dist: scipy
Requires-Dist: tqdm
Requires-Dist: zarr
Provides-Extra: cpu
Requires-Dist: jax~=0.6.2; extra == 'cpu'
Provides-Extra: cuda
Requires-Dist: jax[cuda12]~=0.6.2; extra == 'cuda'
Provides-Extra: dev
Requires-Dist: pytest; extra == 'dev'
Requires-Dist: pytest-cov; extra == 'dev'
Requires-Dist: pytest-xdist; extra == 'dev'
